pds_solar_gen/__init__.py
pds_solar_gen/_version.py
pds_solar_gen/file_defs.py
pds_solar_gen/generator.py
pds_solar_gen/lib_basic.py
pds_solar_gen/lib_floats.py
pds_solar_gen/lib_thrusters.py
pds_solar_gen/main.py
pds_solar_gen-0.1.2.dist-info/LICENSE
pds_solar_gen-0.1.2.dist-info/METADATA
pds_solar_gen-0.1.2.dist-info/WHEEL
pds_solar_gen-0.1.2.dist-info/entry_points.txt
pds_solar_gen-0.1.2.dist-info/top_level.txt
pds_solar_gen-0.1.2.dist-info/RECORD
