Metadata-Version: 2.1
Name: pds-solar-gen
Version: 0.1.2
Summary: ProteusDS floating solar platform generation script.
Author-email: James McVey <53623232+jmcvey3@users.noreply.github.com>
License: BSD 3-Clause License
Keywords: proteus,utils
Classifier: Programming Language :: Python :: 3
Requires-Python: >=3.9
License-File: LICENSE
Requires-Dist: numpy
Requires-Dist: typer >=0.4
Requires-Dist: pyyaml
